plato/__init__.py
plato/__version__.py
plato/context.py
plato/formclasses.py
plato/internal/__init__.py
plato/internal/graph.py
plato/internal/weak_id_dict.py
plato/providers/__init__.py
plato/providers/base.py
plato/providers/common.py
plato/providers/faker.py
plato-0.2.1.dist-info/LICENSE
plato-0.2.1.dist-info/WHEEL
plato-0.2.1.dist-info/METADATA
plato-0.2.1.dist-info/RECORD
