Metadata-Version: 2.1
Name: plato
Version: 0.2.1
Summary: A dataclasses-inspired approach to test data.
Home-page: https://github.com/py-plato/plato
License: MIT
Keywords: testdata,dataclasses
Author: Jan Gosmann
Author-email: jan@hyper-world.de
Maintainer: Jan Gosmann
Maintainer-email: jan@hyper-world.de
Requires-Python: >=3.7,<4.0
Classifier: Development Status :: 2 - Pre-Alpha
Classifier: Intended Audience :: Developers
Classifier: License :: OSI Approved :: MIT License
Classifier: Programming Language :: Python :: 3
Classifier: Programming Language :: Python :: 3.7
Classifier: Programming Language :: Python :: 3.8
Classifier: Programming Language :: Python :: 3.9
Classifier: Topic :: Software Development :: Testing
Classifier: Typing :: Typed
Requires-Dist: Faker (>=8.1.3,<9.0.0)
Requires-Dist: typing-extensions (>=3.7.4,<4.0.0)
Project-URL: Documentation, https://py-plato.github.io/plato/docs/en/stable/
Project-URL: Repository, https://github.com/py-plato/plato
